linker_atom/.DS_Store
linker_atom/__init__.py
linker_atom/api/__init__.py
linker_atom/api/app.py
linker_atom/api/base.py
linker_atom/api/dependencies.py
linker_atom/api/interface/__init__.py
linker_atom/api/interface/healthcheck.py
linker_atom/api/middleware/__init__.py
linker_atom/api/middleware/event.py
linker_atom/api/middleware/http.py
linker_atom/api/route.py
linker_atom/api/schema/__init__.py
linker_atom/api/schema/payload.py
linker_atom/api/schema/response.py
linker_atom/compile_run.py
linker_atom/config/__init__.py
linker_atom/config/logger.py
linker_atom/config/serving.py
linker_atom/config/skywalking.py
linker_atom/dependency/model_protector.so
linker_atom/deploy.py
linker_atom/lib/__init__.py
linker_atom/lib/common.py
linker_atom/lib/exception.py
linker_atom/lib/load_image.py
linker_atom/lib/log.py
linker_atom/lib/requests.py
linker_atom/lib/share_memory.py
linker_atom-0.0.43.dist-info/LICENSE
linker_atom-0.0.43.dist-info/METADATA
linker_atom-0.0.43.dist-info/WHEEL
linker_atom-0.0.43.dist-info/RECORD
