Metadata-Version: 2.1
Name: linker-atom
Version: 0.0.43
Summary: linker fastapi atom
Home-page: https://git.linker.cc/research/common/linker_atom
License: MIT
Author: hanyu
Author-email: han_yu@hzlh.com
Requires-Python: >=3.9,<4.0
Classifier: License :: OSI Approved :: MIT License
Classifier: Operating System :: OS Independent
Classifier: Programming Language :: Python :: 3
Classifier: Programming Language :: Python :: 3.9
Classifier: Programming Language :: Python :: 3.10
Classifier: Programming Language :: Python :: 3.11
Requires-Dist: aiohttp (>=3.10.5,<4.0.0)
Requires-Dist: apache-skywalking (>=1.1.0,<2.0.0)
Requires-Dist: apscheduler (>=3.10.4,<4.0.0)
Requires-Dist: fastapi (>=0.112.2,<0.113.0)
Requires-Dist: numpy
Requires-Dist: opencv-python (==4.7.0.72)
Requires-Dist: orjson (>=3.10.7,<4.0.0)
Requires-Dist: pillow (>=10.4.0,<11.0.0)
Requires-Dist: pydantic (>=2.8.2,<3.0.0)
Requires-Dist: pyinstrument (>=4.7.2,<5.0.0)
Requires-Dist: requests (>=2.32.3,<3.0.0)
Requires-Dist: uvicorn (>=0.30.6,<0.31.0)
Project-URL: Repository, https://git.linker.cc/research/common/linker_atom
